{
    "id": 121047202,
    "name": "i luv spam",
    "author": "polarowy",
    "creators": ["polarowy"],
    "verifier": "polarowy",
    "verification": "https://www.youtube.com/watch?v=jFGZDCQYEMQ",
    "percentToQualify": "100",
    "password": "Free To Copy",
    "records": [
        {
            "user": "Krzak",
            "link": "https://youtu.be/stFD_mnvs44",
            "percent": 100,
            "hz": 144
        },
        {
            "user": "yen",
            "link": "https://www.youtube.com/watch?v=iUwPOOrX-aI",
            "percent": 100,
            "hz": 144
        },
         {
            "user": "beli",
            "link": "https://youtu.be/HC6Q14b4sW0?si=6d01Evs6SR66MMMi",
            "percent": 100,
            "hz": 144
        },
         {
            "user": "Mateusz001",
            "link": "https://www.youtube.com/watch?v=VE_o0aaW7YI",
            "percent": 100,
            "hz": 240
        },
        {
            "user": "Blobik mlemowski",
            "link": "https://www.youtube.com/watch?v=U0qvwdXyW1o",
            "percent": 100,
            "hz": 240
        }
    ]
}
