{
    "id": 127269285,
    "name": "Przemek Challenge",
    "author": "FranekGMD",
    "creators": ["FranekGMD"],
    "verifier": "FranekGMD",
    "verification": "https://youtu.be/ADt5OZPKICE",
    "percentToQualify": "100",
    "password": "Free To Copy",
    "records": [
        {
            "user": "Kuboiks",
            "link": "https://www.youtube.com/watch?v=14khsvNaFx0",
            "percent": 100,
            "hz": 1080
        },
        {
            "user": "Cinasek",
            "link": "https://www.youtube.com/watch?v=Oe703aeiQU4",
            "percent": 100,
            "hz": 240
        },
        {
            "user": "szymek",
            "link": "https://www.youtube.com/watch?v=2lyW-D1e4ZE",
            "percent": 100,
            "hz": 60
        }
    ]
}
